smallgraphlib/__init__.py
smallgraphlib/automatons.py
smallgraphlib/basic_graphs.py
smallgraphlib/core.py
smallgraphlib/custom_types.py
smallgraphlib/flow_networks.py
smallgraphlib/graphs_constructors.py
smallgraphlib/huffman.py
smallgraphlib/labeled_graphs.py
smallgraphlib/markov_chain.py
smallgraphlib/printers/__init__.py
smallgraphlib/printers/latex.py
smallgraphlib/printers/tikz.py
smallgraphlib/py.typed
smallgraphlib/string2automaton.py
smallgraphlib/trees.py
smallgraphlib/utilities.py
smallgraphlib/weighted_graphs.py
smallgraphlib-1.1.0.dist-info/METADATA
smallgraphlib-1.1.0.dist-info/WHEEL
smallgraphlib-1.1.0.dist-info/RECORD
