Metadata-Version: 2.1
Name: smallgraphlib
Version: 1.1.0
Summary: Simple library for handling small graphs, including Tikz code generation.
Home-page: https://github.com/wxgeo/smallgraphlib
License: GPL-3.0-or-later
Keywords: graph,tikz,latex
Author: Nicolas Pourcelot
Author-email: nicolas.pourcelot@gmail.com
Requires-Python: >=3.10,<4.0
Classifier: License :: OSI Approved :: GNU General Public License v3 or later (GPLv3+)
Classifier: Programming Language :: Python :: 3
Classifier: Programming Language :: Python :: 3.10
Classifier: Programming Language :: Python :: 3.11
Classifier: Programming Language :: Python :: 3.12
Project-URL: Repository, https://github.com/wxgeo/smallgraphlib
